sphinx_variations-1.0.5.dist-info/METADATA
sphinx_variations-1.0.5.dist-info/RECORD
sphinx_variations-1.0.5.dist-info/WHEEL
sphinx_variations-1.0.5.dist-info/top_level.txt
variations/__init__.py
