Metadata-Version: 2.1
Name: sphinx-variations
Version: 1.0.5
Summary: Create multiple variations of your Sphinx HTML documentation.
Home-page: https://github.com/treamology/sphinx-variations
Author: D. Lawrence
Author-email: trea@treamous.com
License: UNKNOWN
Platform: UNKNOWN
Classifier: Programming Language :: Python :: 3
Classifier: License :: OSI Approved :: MIT License
Classifier: Operating System :: OS Independent
Classifier: Framework :: Sphinx
Classifier: Topic :: Documentation
Classifier: Topic :: Software Development :: Documentation
Requires-Dist: sphinx
